jupyterlab_hello/__init__.py
jupyterlab_hello/_version.py
jupyterlab_hello-0.1.1a0.data/data/share/jupyter/labextensions/jupyterlab-hello/package.json
jupyterlab_hello-0.1.1a0.data/data/share/jupyter/labextensions/jupyterlab-hello/static/509.8c8e6dc6e74c9930f0b6.js
jupyterlab_hello-0.1.1a0.data/data/share/jupyter/labextensions/jupyterlab-hello/static/728.c2e72999f90b55e0dcef.js
jupyterlab_hello-0.1.1a0.data/data/share/jupyter/labextensions/jupyterlab-hello/static/remoteEntry.4df30c52876cfa828328.js
jupyterlab_hello-0.1.1a0.data/data/share/jupyter/labextensions/jupyterlab-hello/static/style.js
jupyterlab_hello-0.1.1a0.data/data/share/jupyter/labextensions/jupyterlab-hello/static/third-party-licenses.json
jupyterlab_hello-0.1.1a0.data/data/share/jupyter/labextensions/jupyterlab-hello/install.json
jupyterlab_hello-0.1.1a0.dist-info/METADATA
jupyterlab_hello-0.1.1a0.dist-info/WHEEL
jupyterlab_hello-0.1.1a0.dist-info/licenses/LICENSE
jupyterlab_hello-0.1.1a0.dist-info/RECORD
